{
  "id": "rni8XqI1u8Mds3aIuzKlDcRu2hV2",
  "name": "Unknown",
  "place": "Indi",
  "lat": 16.04,
  "lon": 75.14,
  "birthdate": "2001-04-17",
  "birthtime": "14:00",
  "julian_day": 2452017.0833333335,
  "ascendant": {
    "longitude": 219.03,
    "sign": "Scorpio",
    "deg_in_sign": 9.03
  },
  "midheaven": {
    "longitude": 128.48,
    "sign": "Leo",
    "deg_in_sign": 8.48
  },
  "houses": [
    219.03,
    248.28,
    277.85,
    308.48,
    340.13,
    10.96,
    39.03,
    68.28,
    97.85,
    128.48,
    160.13,
    190.96
  ],
  "planets": {
    "Sun": {
      "longitude": 27.61,
      "sign": "Aries",
      "deg_in_sign": 27.61
    },
    "Moon": {
      "longitude": 318.62,
      "sign": "Aquarius",
      "deg_in_sign": 18.62
    },
    "Mercury": {
      "longitude": 21.22,
      "sign": "Aries",
      "deg_in_sign": 21.22
    },
    "Venus": {
      "longitude": 1.59,
      "sign": "Aries",
      "deg_in_sign": 1.59
    },
    "Mars": {
      "longitude": 265.84,
      "sign": "Sagittarius",
      "deg_in_sign": 25.84
    },
    "Jupiter": {
      "longitude": 70.72,
      "sign": "Gemini",
      "deg_in_sign": 10.72
    },
    "Saturn": {
      "longitude": 59.61,
      "sign": "Taurus",
      "deg_in_sign": 29.61
    },
    "Uranus": {
      "longitude": 324.13,
      "sign": "Aquarius",
      "deg_in_sign": 24.13
    },
    "Neptune": {
      "longitude": 308.63,
      "sign": "Aquarius",
      "deg_in_sign": 8.63
    },
    "Pluto": {
      "longitude": 255.03,
      "sign": "Sagittarius",
      "deg_in_sign": 15.03
    },
    "North Node": {
      "longitude": 100.04,
      "sign": "Cancer",
      "deg_in_sign": 10.04
    },
    "South Node": {
      "longitude": 280.04,
      "sign": "Capricorn",
      "deg_in_sign": 10.04
    }
  },
  "nodes": {
    "North Node": {
      "longitude": 100.04,
      "sign": "Cancer",
      "deg_in_sign": 10.04
    },
    "South Node": {
      "longitude": 280.04,
      "sign": "Capricorn",
      "deg_in_sign": 10.04
    }
  }
}