{
  "id": "XyqGWvDNNaZFtHBK76Y8Nofdt6H2",
  "name": "sreepurna bhattacharya",
  "place": "Badaun, uttarpradesh",
  "lat": 28.6,
  "lon": 79.42,
  "birthdate": "1999-04-22",
  "birthtime": "05:55",
  "julian_day": 2451290.746527778,
  "ascendant": {
    "longitude": 117.77,
    "sign": "Cancer",
    "deg_in_sign": 27.77
  },
  "midheaven": {
    "longitude": 19.53,
    "sign": "Aries",
    "deg_in_sign": 19.53
  },
  "houses": [
    117.77,
    141.03,
    167.92,
    199.53,
    233.96,
    267.36,
    297.77,
    321.03,
    347.92,
    19.53,
    53.96,
    87.36
  ],
  "planets": {
    "Sun": {
      "longitude": 31.67,
      "sign": "Taurus",
      "deg_in_sign": 1.67
    },
    "Moon": {
      "longitude": 114.81,
      "sign": "Cancer",
      "deg_in_sign": 24.81
    },
    "Mercury": {
      "longitude": 4.91,
      "sign": "Aries",
      "deg_in_sign": 4.91
    },
    "Venus": {
      "longitude": 71.3,
      "sign": "Gemini",
      "deg_in_sign": 11.3
    },
    "Mars": {
      "longitude": 215.02,
      "sign": "Scorpio",
      "deg_in_sign": 5.02
    },
    "Jupiter": {
      "longitude": 16.12,
      "sign": "Aries",
      "deg_in_sign": 16.12
    },
    "Saturn": {
      "longitude": 36.09,
      "sign": "Taurus",
      "deg_in_sign": 6.09
    },
    "Uranus": {
      "longitude": 316.43,
      "sign": "Aquarius",
      "deg_in_sign": 16.43
    },
    "Neptune": {
      "longitude": 304.31,
      "sign": "Aquarius",
      "deg_in_sign": 4.31
    },
    "Pluto": {
      "longitude": 250.09,
      "sign": "Sagittarius",
      "deg_in_sign": 10.09
    },
    "North Node": {
      "longitude": 138.5,
      "sign": "Leo",
      "deg_in_sign": 18.5
    },
    "South Node": {
      "longitude": 318.5,
      "sign": "Aquarius",
      "deg_in_sign": 18.5
    }
  },
  "north_node": {
    "longitude": 138.5,
    "sign": "Leo",
    "deg_in_sign": 18.5
  },
  "south_node": {
    "longitude": 318.5,
    "sign": "Aquarius",
    "deg_in_sign": 18.5
  }
}